densor.py
dynamic_tensor-0.0.2.dist-info/LICENSE
dynamic_tensor-0.0.2.dist-info/METADATA
dynamic_tensor-0.0.2.dist-info/WHEEL
dynamic_tensor-0.0.2.dist-info/top_level.txt
dynamic_tensor-0.0.2.dist-info/RECORD
