Metadata-Version: 2.1
Name: dynamic-tensor
Version: 0.0.2
Summary: Automatically and minimally expanding tensor for __setitem()__ operations based on NumPy.
Home-page: https://github.com/eurekazheng/dynamic-tensor
Author: Shaoming Zheng
Author-email: zhengeureka@gmail.com
Maintainer: Shaoming Zheng
Maintainer-email: zhengeureka@gmail.com
License: MIT
Keywords: tensor,numpy,array
Platform: any
Classifier: Programming Language :: Python :: 3
Classifier: License :: OSI Approved :: MIT License
Classifier: Operating System :: OS Independent
Requires-Python: >=3.6
License-File: LICENSE
Requires-Dist: numpy (>=1.16)
